MANIFEST.in
README.md
README.zh-CN.md
requirements.txt
setup.py
keras_multi_head/__init__.py
keras_multi_head/multi_head.py
keras_multi_head/multi_head_attention.py
keras_multi_head.egg-info/PKG-INFO
keras_multi_head.egg-info/SOURCES.txt
keras_multi_head.egg-info/dependency_links.txt
keras_multi_head.egg-info/requires.txt
keras_multi_head.egg-info/top_level.txt
tests/__init__.py
tests/multi_head_attention_brute.py
tests/test_mapping.py
tests/test_multi_head.py
tests/test_multi_head_attention.py
tests/test_regularization.py