Metadata-Version: 2.1
Name: keras-multi-head
Version: 0.29.0
Summary: A wrapper layer for stacking layers horizontally
Home-page: https://github.com/CyberZHG/keras-multi-head
Author: CyberZHG
Author-email: CyberZHG@users.noreply.github.com
License: MIT
Platform: UNKNOWN
Classifier: Programming Language :: Python :: 3
Classifier: License :: OSI Approved :: MIT License
Classifier: Operating System :: OS Independent
